llama_index/py.typed
llama_index/vector_stores/milvus/__init__.py
llama_index/vector_stores/milvus/base.py
llama_index/vector_stores/milvus/utils.py
llama_index_vector_stores_milvus-0.9.5.dist-info/METADATA
llama_index_vector_stores_milvus-0.9.5.dist-info/WHEEL
llama_index_vector_stores_milvus-0.9.5.dist-info/licenses/LICENSE
llama_index_vector_stores_milvus-0.9.5.dist-info/RECORD
