Metadata-Version: 2.4
Name: llama-index-vector-stores-milvus
Version: 0.9.5
Summary: llama-index vector_stores milvus integration
License-Expression: MIT
License-File: LICENSE
Requires-Python: <4.0,>=3.9
Requires-Dist: llama-index-core<0.15,>=0.13.0
Requires-Dist: pymilvus<3,>=2.5.10
